torbox/__init__.py
torbox/cli.py
torbox/client.py
torbox/services/__init__.py
torbox/services/base.py
torbox/services/rss.py
torbox/services/stats.py
torbox/services/torrents.py
torbox/services/usenet.py
torbox/services/user.py
torbox/services/webdl.py
torbox/services/integrations/__init__.py
TorBox-0.1.0a1.dist-info/LICENSE
TorBox-0.1.0a1.dist-info/METADATA
TorBox-0.1.0a1.dist-info/WHEEL
TorBox-0.1.0a1.dist-info/entry_points.txt
TorBox-0.1.0a1.dist-info/top_level.txt
TorBox-0.1.0a1.dist-info/RECORD
